<Module>
  <Name value="AlwaysKeepHorsesAndFood"/>
  <Id value="AlwaysKeepHorsesAndFood"/>
  <Version value="v0.3.4"/>
  <SingleplayerModule value="true"/>
  <MultiplayerModule value="false"/>
  <Official value="false"/>
  <DependedModules>
    <DependedModule Id="Native"/>
    <DependedModule Id="SandBoxCore"/>
    <DependedModule Id="Sandbox"/>
    <DependedModule Id="CustomBattle"/>
    <DependedModule Id="StoryMode" />
  </DependedModules>
  <SubModules>
    <!-- The following SubModule element is optional. You can remove this portion if your mod does not have a DLL associated with it. -->
    <SubModule>
      <Name value="AlwaysKeepHorsesAndFood"/>
      <!-- Path to the DLL File, if your Mod is called MyModule then it should be   -->
      <DLLName value="AlwaysKeepHorsesAndFood.dll"/>
      <SubModuleClassType value="AlwaysKeepHorsesAndFood.FastLootSubModule"/>
      <Tags>
        <Tag key="DedicatedServerType" value="none" />
        <Tag key="IsNoRenderModeElement" value="false" />
      </Tags>
    </SubModule>
    
  </SubModules>
  <Xmls>
  </Xmls>
</Module>